gradio_polygonannotator/__init__.py
gradio_polygonannotator/polygonannotator.py
gradio_polygonannotator/polygonannotator.pyi
gradio_polygonannotator/templates/component/Index-CzQ497_5.js
gradio_polygonannotator/templates/component/SharedSystems-Cd96rNl9.js
gradio_polygonannotator/templates/component/WebGLRenderer-CcnJ7_Ew.js
gradio_polygonannotator/templates/component/WebGPURenderer-CLzW5yah.js
gradio_polygonannotator/templates/component/browserAll-BoGsSDHg.js
gradio_polygonannotator/templates/component/colorToUniform-zJcCVLeu.js
gradio_polygonannotator/templates/component/index.js
gradio_polygonannotator/templates/component/style.css
gradio_polygonannotator/templates/component/webworkerAll-BMMxBtBd.js
gradio_polygonannotator/templates/example/index.js
gradio_polygonannotator/templates/example/style.css
gradio_polygonannotator-0.2.1.dist-info/METADATA
gradio_polygonannotator-0.2.1.dist-info/WHEEL
gradio_polygonannotator-0.2.1.dist-info/RECORD
