Metadata-Version: 2.4
Name: gradio_polygonannotator
Version: 0.2.1
Summary: Interactive polygon annotation component for Gradio with multi-selection, hover effects, and customizable appearance
Project-URL: repository, https://github.com/yourusername/gradio-polygonannotator
Author-email: Borg93 <gabriel.borg@riksarkivet.se>
License-Expression: Apache-2.0
Keywords: document-analysis,gradio-custom-component,image-annotation,interactive-visualization,polygon-annotation
Classifier: Development Status :: 3 - Alpha
Classifier: Operating System :: OS Independent
Classifier: Programming Language :: Python :: 3
Classifier: Programming Language :: Python :: 3 :: Only
Classifier: Programming Language :: Python :: 3.8
Classifier: Programming Language :: Python :: 3.9
Classifier: Programming Language :: Python :: 3.10
Classifier: Programming Language :: Python :: 3.11
Classifier: Topic :: Scientific/Engineering
Classifier: Topic :: Scientific/Engineering :: Artificial Intelligence
Classifier: Topic :: Scientific/Engineering :: Visualization
Requires-Python: >=3.8
Requires-Dist: gradio<6.0,>=4.0
Provides-Extra: dev
Requires-Dist: build; extra == 'dev'
Requires-Dist: twine; extra == 'dev'
